mcp_arena/__init__.py
mcp_arena/cli.py
mcp_arena/main.py
mcp_arena/agent/__init__.py
mcp_arena/agent/base.py
mcp_arena/agent/factory.py
mcp_arena/agent/interfaces.py
mcp_arena/agent/memory.py
mcp_arena/agent/planning_agent.py
mcp_arena/agent/policies.py
mcp_arena/agent/react_agent.py
mcp_arena/agent/reflection_agent.py
mcp_arena/agent/router.py
mcp_arena/agent/state.py
mcp_arena/agent/tools.py
mcp_arena/examples/agent_examples.py
mcp_arena/mcp/__init__.py
mcp_arena/mcp/registry.py
mcp_arena/mcp/server.py
mcp_arena/presents/__init__.py
mcp_arena/presents/aws.py
mcp_arena/presents/bitbucket.py
mcp_arena/presents/confluence.py
mcp_arena/presents/docker.py
mcp_arena/presents/generic_api.py
mcp_arena/presents/github.py
mcp_arena/presents/gitlab.py
mcp_arena/presents/jira.py
mcp_arena/presents/local_operation.py
mcp_arena/presents/mail.py
mcp_arena/presents/mongo.py
mcp_arena/presents/notion.py
mcp_arena/presents/outlook.py
mcp_arena/presents/postgres.py
mcp_arena/presents/redis.py
mcp_arena/presents/slack.py
mcp_arena/presents/smtp.py
mcp_arena/presents/vectordb.py
mcp_arena/presents/whatsapp.py
mcp_arena/tools/__init__.py
mcp_arena/tools/agent_tool.py
mcp_arena/tools/base.py
mcp_arena/tools/bitbucket.py
mcp_arena/tools/calculator.py
mcp_arena/tools/data_analysis.py
mcp_arena/tools/docker.py
mcp_arena/tools/filesystem.py
mcp_arena/tools/github.py
mcp_arena/tools/gitlab.py
mcp_arena/tools/jira.py
mcp_arena/tools/local_operation.py
mcp_arena/tools/mongo.py
mcp_arena/tools/notion.py
mcp_arena/tools/postgres.py
mcp_arena/tools/redis.py
mcp_arena/tools/search.py
mcp_arena/tools/slack.py
mcp_arena/tools/time_tool.py
mcp_arena/tools/vectordb.py
mcp_arena/tools/web.py
mcp_arena/wrapper/__init__.py
mcp_arena/wrapper/agent_wrapper.py
mcp_arena/wrapper/langchain_integration.py
mcp_arena/wrapper/langchain_wrapper.py
mcp_arena-0.2.3.dist-info/METADATA
mcp_arena-0.2.3.dist-info/WHEEL
mcp_arena-0.2.3.dist-info/entry_points.txt
mcp_arena-0.2.3.dist-info/licenses/LICENSE
mcp_arena-0.2.3.dist-info/RECORD
