Metadata-Version: 2.4
Name: mcp_arena
Version: 0.2.3
Summary: An opinionated Python library for building MCP (Model Context Protocol) servers with presets, agents, and tools.
Project-URL: Homepage, https://github.com/SatyamSingh8306/mcp_arena
Project-URL: Repository, https://github.com/SatyamSingh8306/mcp_arena
Project-URL: Issues, https://github.com/SatyamSingh8306/mcp_arena/issues
Author-email: Satyam Singh <satyamsingh7734@gmail.com>
License: MIT
License-File: LICENSE
Keywords: agents,ai,llm,mcp,model-context-protocol
Classifier: Development Status :: 3 - Alpha
Classifier: Intended Audience :: Developers
Classifier: License :: OSI Approved :: MIT License
Classifier: Operating System :: OS Independent
Classifier: Programming Language :: Python :: 3.12
Requires-Python: >=3.12
Requires-Dist: atlassian-python-api>=4.0.7
Requires-Dist: boto3>=1.42.15
Requires-Dist: chromadb<2.0,>=1.3.5
Requires-Dist: docker>=7.1.0
Requires-Dist: google-api-python-client<3.0,>=2.130
Requires-Dist: google-auth-httplib2<1.0,>=0.1.0
Requires-Dist: google-auth-oauthlib<2.0,>=1.2
Requires-Dist: google-auth<3.0,>=2.29
Requires-Dist: html2text>=2025.4.15
Requires-Dist: langchain-chroma<2.0,>=1.1
Requires-Dist: langchain-community<1.0,>=0.4
Requires-Dist: langchain-core<2.0,>=1.2
Requires-Dist: langchain-groq>=1.1.1
Requires-Dist: langchain-huggingface<2.0,>=1.2
Requires-Dist: langchain-mcp-adapters>=0.2.1
Requires-Dist: langchain-openai<2.0,>=1.1
Requires-Dist: langchain<2.0,>=1.2
Requires-Dist: mcp<2.0,>=1.25
Requires-Dist: msal<2.0,>=1.28
Requires-Dist: notion-client>=2.7.0
Requires-Dist: psutil<8.0,>=7.2
Requires-Dist: psycopg2-binary>=2.9.11
Requires-Dist: pyautogui>=0.9.54
Requires-Dist: pygithub<3.0,>=2.8
Requires-Dist: pymongo>=4.15.5
Requires-Dist: python-dotenv<2.0,>=1.0
Requires-Dist: python-gitlab>=7.0.0
Requires-Dist: redis>=7.1.0
Requires-Dist: requests<3.0,>=2.31
Requires-Dist: rich>=13.0.0
Requires-Dist: sentence-transformers<6.0,>=5.2
Requires-Dist: slack-sdk<4.0,>=3.27
Requires-Dist: twilio<10.0,>=9.0
Requires-Dist: typer>=0.9.0
Requires-Dist: typing-extensions<5.0,>=4.8
Provides-Extra: agents
Requires-Dist: langchain-agent<1.0,>=0.1; extra == 'agents'
Requires-Dist: langchain-groq<2.0,>=1.0; extra == 'agents'
Requires-Dist: langchain-mcp-adapters<1.0,>=0.1; extra == 'agents'
Provides-Extra: all
Requires-Dist: atlassian-python-api<5.0,>=4.0; extra == 'all'
Requires-Dist: chromadb<2.0,>=1.3.5; extra == 'all'
Requires-Dist: docker<8.0,>=7.1; extra == 'all'
Requires-Dist: google-api-python-client<3.0,>=2.130; extra == 'all'
Requires-Dist: google-auth-httplib2<1.0,>=0.1.0; extra == 'all'
Requires-Dist: google-auth-oauthlib<2.0,>=1.2; extra == 'all'
Requires-Dist: google-auth<3.0,>=2.29; extra == 'all'
Requires-Dist: kubernetes<35.0,>=28.1; extra == 'all'
Requires-Dist: langchain-agent<1.0,>=0.1; extra == 'all'
Requires-Dist: langchain-groq<2.0,>=1.0; extra == 'all'
Requires-Dist: langchain-mcp-adapters<1.0,>=0.1; extra == 'all'
Requires-Dist: msal<2.0,>=1.28; extra == 'all'
Requires-Dist: psutil<8.0,>=7.2; extra == 'all'
Requires-Dist: psycopg2-binary<3.0,>=2.9; extra == 'all'
Requires-Dist: pyautogui<1.0,>=0.9; extra == 'all'
Requires-Dist: pygithub<3.0,>=2.8; extra == 'all'
Requires-Dist: pymongo<5.0,>=4.6; extra == 'all'
Requires-Dist: python-gitlab<8.0,>=7.0; extra == 'all'
Requires-Dist: redis<8.0,>=5.0; extra == 'all'
Requires-Dist: sentence-transformers<6.0,>=5.2; extra == 'all'
Requires-Dist: slack-sdk<4.0,>=3.27; extra == 'all'
Requires-Dist: twilio<10.0,>=9.0; extra == 'all'
Provides-Extra: bitbucket
Requires-Dist: atlassian-python-api<5.0,>=4.0; extra == 'bitbucket'
Provides-Extra: communication
Requires-Dist: google-api-python-client<3.0,>=2.130; extra == 'communication'
Requires-Dist: google-auth-httplib2<1.0,>=0.1.0; extra == 'communication'
Requires-Dist: google-auth-oauthlib<2.0,>=1.2; extra == 'communication'
Requires-Dist: google-auth<3.0,>=2.29; extra == 'communication'
Requires-Dist: msal<2.0,>=1.28; extra == 'communication'
Requires-Dist: slack-sdk<4.0,>=3.27; extra == 'communication'
Requires-Dist: twilio<10.0,>=9.0; extra == 'communication'
Provides-Extra: complete
Requires-Dist: atlassian-python-api<5.0,>=4.0; extra == 'complete'
Requires-Dist: black<26.0,>=24.0; extra == 'complete'
Requires-Dist: chromadb<2.0,>=1.3.5; extra == 'complete'
Requires-Dist: docker<8.0,>=7.1; extra == 'complete'
Requires-Dist: google-api-python-client<3.0,>=2.130; extra == 'complete'
Requires-Dist: google-auth-httplib2<1.0,>=0.1.0; extra == 'complete'
Requires-Dist: google-auth-oauthlib<2.0,>=1.2; extra == 'complete'
Requires-Dist: google-auth<3.0,>=2.29; extra == 'complete'
Requires-Dist: isort<6.0,>=5.12; extra == 'complete'
Requires-Dist: kubernetes<35.0,>=28.1; extra == 'complete'
Requires-Dist: langchain-agent<1.0,>=0.1; extra == 'complete'
Requires-Dist: langchain-groq<2.0,>=1.0; extra == 'complete'
Requires-Dist: langchain-mcp-adapters<1.0,>=0.1; extra == 'complete'
Requires-Dist: msal<2.0,>=1.28; extra == 'complete'
Requires-Dist: mypy<2.0,>=1.7; extra == 'complete'
Requires-Dist: pre-commit<4.0,>=3.5; extra == 'complete'
Requires-Dist: psutil<8.0,>=7.2; extra == 'complete'
Requires-Dist: psycopg2-binary<3.0,>=2.9; extra == 'complete'
Requires-Dist: pyautogui<1.0,>=0.9; extra == 'complete'
Requires-Dist: pygithub<3.0,>=2.8; extra == 'complete'
Requires-Dist: pymongo<5.0,>=4.6; extra == 'complete'
Requires-Dist: pytest-asyncio<1.0,>=0.23; extra == 'complete'
Requires-Dist: pytest<9.0,>=8.0; extra == 'complete'
Requires-Dist: python-gitlab<8.0,>=7.0; extra == 'complete'
Requires-Dist: redis<8.0,>=5.0; extra == 'complete'
Requires-Dist: ruff<1.0,>=0.12; extra == 'complete'
Requires-Dist: sentence-transformers<6.0,>=5.2; extra == 'complete'
Requires-Dist: slack-sdk<4.0,>=3.27; extra == 'complete'
Requires-Dist: twilio<10.0,>=9.0; extra == 'complete'
Provides-Extra: dev
Requires-Dist: black<26.0,>=24.0; extra == 'dev'
Requires-Dist: isort<6.0,>=5.12; extra == 'dev'
Requires-Dist: mypy<2.0,>=1.7; extra == 'dev'
Requires-Dist: pre-commit<4.0,>=3.5; extra == 'dev'
Requires-Dist: pytest-asyncio<1.0,>=0.23; extra == 'dev'
Requires-Dist: pytest<9.0,>=8.0; extra == 'dev'
Requires-Dist: ruff<1.0,>=0.12; extra == 'dev'
Provides-Extra: docker
Requires-Dist: docker<8.0,>=7.1; extra == 'docker'
Provides-Extra: email
Requires-Dist: google-api-python-client<3.0,>=2.130; extra == 'email'
Requires-Dist: google-auth-httplib2<1.0,>=0.1.0; extra == 'email'
Requires-Dist: google-auth-oauthlib<2.0,>=1.2; extra == 'email'
Requires-Dist: google-auth<3.0,>=2.29; extra == 'email'
Requires-Dist: msal<2.0,>=1.28; extra == 'email'
Provides-Extra: github
Requires-Dist: pygithub<3.0,>=2.8; extra == 'github'
Provides-Extra: gitlab
Requires-Dist: python-gitlab<8.0,>=7.0; extra == 'gitlab'
Provides-Extra: gmail
Requires-Dist: google-api-python-client<3.0,>=2.130; extra == 'gmail'
Requires-Dist: google-auth-httplib2<1.0,>=0.1.0; extra == 'gmail'
Requires-Dist: google-auth-oauthlib<2.0,>=1.2; extra == 'gmail'
Requires-Dist: google-auth<3.0,>=2.29; extra == 'gmail'
Provides-Extra: kubernetes
Requires-Dist: kubernetes<35.0,>=28.1; extra == 'kubernetes'
Provides-Extra: local-operation
Requires-Dist: psutil<8.0,>=7.2; extra == 'local-operation'
Requires-Dist: pyautogui<1.0,>=0.9; extra == 'local-operation'
Provides-Extra: messaging
Requires-Dist: slack-sdk<4.0,>=3.27; extra == 'messaging'
Requires-Dist: twilio<10.0,>=9.0; extra == 'messaging'
Provides-Extra: mongodb
Requires-Dist: pymongo<5.0,>=4.6; extra == 'mongodb'
Provides-Extra: outlook
Requires-Dist: msal<2.0,>=1.28; extra == 'outlook'
Provides-Extra: postgres
Requires-Dist: psycopg2-binary<3.0,>=2.9; extra == 'postgres'
Provides-Extra: redis
Requires-Dist: redis<8.0,>=5.0; extra == 'redis'
Provides-Extra: slack
Requires-Dist: slack-sdk<4.0,>=3.27; extra == 'slack'
Provides-Extra: vectordb
Requires-Dist: chromadb<2.0,>=1.3.5; extra == 'vectordb'
Requires-Dist: sentence-transformers<6.0,>=5.2; extra == 'vectordb'
Provides-Extra: whatsapp
Requires-Dist: twilio<10.0,>=9.0; extra == 'whatsapp'
